<annotation>
	<folder>train</folder>
	<filename>4.jpg</filename>
	<path>G:\Github\Self driving Car\models\object_detection\train\4.jpg</path>
	<source>
		<database>Unknown</database>
	</source>
	<size>
		<width>4000</width>
		<height>2250</height>
		<depth>3</depth>
	</size>
	<segmented>0</segmented>
	<object>
		<name>Person</name>
		<pose>Unspecified</pose>
		<truncated>0</truncated>
		<difficult>0</difficult>
		<bndbox>
			<xmin>315</xmin>
			<ymin>615</ymin>
			<xmax>485</xmax>
			<ymax>865</ymax>
		</bndbox>
	</object>
	<object>
		<name>Person</name>
		<pose>Unspecified</pose>
		<truncated>0</truncated>
		<difficult>0</difficult>
		<bndbox>
			<xmin>2875</xmin>
			<ymin>265</ymin>
			<xmax>3025</xmax>
			<ymax>585</ymax>
		</bndbox>
	</object>
	<object>
		<name>Person</name>
		<pose>Unspecified</pose>
		<truncated>0</truncated>
		<difficult>0</difficult>
		<bndbox>
			<xmin>3725</xmin>
			<ymin>1175</ymin>
			<xmax>3915</xmax>
			<ymax>1545</ymax>
		</bndbox>
	</object>
</annotation>
